devops_client/__init__.py
devops_client/common.py
devops_client/task_management.py
devops_mcp_server-0.1.0.dist-info/METADATA
devops_mcp_server-0.1.0.dist-info/WHEEL
devops_mcp_server-0.1.0.dist-info/top_level.txt
devops_mcp_server-0.1.0.dist-info/RECORD
